pdfsplicer/__init__.py
pdfsplicer/ranges.py
pdfsplicer/utils.py
pdfsplicer-0.0.3.dist-info/licenses/LICENCE
pdfsplicer-0.0.3.dist-info/METADATA
pdfsplicer-0.0.3.dist-info/WHEEL
pdfsplicer-0.0.3.dist-info/entry_points.txt
pdfsplicer-0.0.3.dist-info/top_level.txt
pdfsplicer-0.0.3.dist-info/RECORD
