Metadata-Version: 2.4
Name: pdfsplicer
Version: 0.0.3
Summary: A CLI to splice and dice your PDFs
License-Expression: GPL-3.0
Project-URL: repository, https://codeberg.org/jamesansley/pdfsplicer
License-File: LICENCE
Requires-Dist: pypdf~=6.6.0
Dynamic: license-file
